CHANGELOG.rst
CONTRIBUTORS.rst
LICENSE.txt
MANIFEST.in
README.rst
requirements.txt
setup.py
docs/Makefile
docs/__init__.py
docs/conf.py
docs/index.rst
docs/api/api.rst
docs/api/settings.rst
docs/api/urn_nbn_api.rst
docs/api/xml_composer.rst
docs/api/xml_convertor.rst
docs/api/api_structures/api_structures.rst
docs/api/api_structures/catalog.rst
docs/api/api_structures/digital_instance.rst
docs/api/api_structures/digital_library.rst
docs/api/api_structures/modes.rst
docs/api/api_structures/registrar.rst
docs/api/api_structures/tools.rst
docs/api/api_structures/urn_nbn.rst
docs/example/example.rst
src/cz_urnnbn_api/__init__.py
src/cz_urnnbn_api/api.py
src/cz_urnnbn_api/settings.py
src/cz_urnnbn_api/xml_composer.py
src/cz_urnnbn_api/xml_convertor.py
src/cz_urnnbn_api.egg-info/PKG-INFO
src/cz_urnnbn_api.egg-info/SOURCES.txt
src/cz_urnnbn_api.egg-info/dependency_links.txt
src/cz_urnnbn_api.egg-info/not-zip-safe
src/cz_urnnbn_api.egg-info/requires.txt
src/cz_urnnbn_api.egg-info/top_level.txt
src/cz_urnnbn_api/api_structures/__init__.py
src/cz_urnnbn_api/api_structures/catalog.py
src/cz_urnnbn_api/api_structures/digital_instance.py
src/cz_urnnbn_api/api_structures/digital_library.py
src/cz_urnnbn_api/api_structures/modes.py
src/cz_urnnbn_api/api_structures/registrar.py
src/cz_urnnbn_api/api_structures/tools.py
src/cz_urnnbn_api/api_structures/urn_nbn.py
tests/integration/test_api.py
tests/unit/__init__.py
tests/unit/test_rest.py
tests/unit/test_xml_composer.py
tests/unit/test_xml_convertor.py
tests/unit/api_structures/__init__.py
tests/unit/api_structures/test_digital_instance.py
tests/unit/api_structures/test_modes.py
tests/unit/api_structures/test_tools.py
tests/unit/data/digital_instances.xml
tests/unit/data/iter_registrars_data.xml
tests/unit/data/mods_mono.xml
tests/unit/data/mono_output.xml
tests/unit/data/mono_volume_output.xml
tests/unit/data/no_digital_instance.xml
tests/unit/data/registrar_data.xml
tests/unit/data/registration_response.xml
tests/unit/data/additional_examples/1444650215-028126-mods.xml
tests/unit/data/additional_examples/1444650216-229482-mods.xml
tests/unit/data/additional_examples/1444650216-637581-mods.xml
tests/unit/data/additional_examples/1444650217-076478-mods.xml