Metadata-Version: 1.1
Name: cz-urnnbn-api
Version: 0.2.6
Summary: API for the Czech URN:NBN resolver (https://resolver.nkp.cz).
Home-page: https://github.com/edeposit/cz-urnnbn-api/
Author: Edeposit team
Author-email: edeposit@email.cz
License: MIT
Platform: UNKNOWN
Classifier: Development Status :: 3 - Alpha
Classifier: Programming Language :: Python
Classifier: Programming Language :: Python :: 2.7
Classifier: Intended Audience :: Developers
Classifier: Topic :: Software Development :: Libraries
Classifier: Topic :: Software Development :: Libraries :: Python Modules
Classifier: Topic :: Communications :: File Sharing
Classifier: License :: OSI Approved :: MIT License
